emailee/__init__.py
emailee/emailee.py
emailee/emailee_async.py
emailee-1.0.0.dist-info/LICENSE
emailee-1.0.0.dist-info/WHEEL
emailee-1.0.0.dist-info/METADATA
emailee-1.0.0.dist-info/RECORD
