Metadata-Version: 2.1
Name: emailee
Version: 1.0.0
Summary: A robust smtp email send tool, with asyncronous send capability
Home-page: http://github.com/mattwalshdev/emailee
License: MIT
Author: Matt Walsh
Author-email: git@mattwalsh.dev
Requires-Python: >=3.6.1,<4.0.0
Classifier: Development Status :: 5 - Production/Stable
Classifier: License :: OSI Approved :: MIT License
Classifier: Natural Language :: English
Classifier: Programming Language :: Python :: 3
Classifier: Programming Language :: Python :: 3.7
Classifier: Programming Language :: Python :: 3.8
Classifier: Programming Language :: Python :: 3.9
Classifier: Topic :: Communications :: Email
Classifier: Topic :: Communications :: Email :: Mail Transport Agents
Project-URL: Documentation, http://github.com/mattwalshdev/emailee/README.md
Project-URL: Repository, http://github.com/mattwalshdev/emailee
